mcrs/__init__.py
mcrs/execution_context.py
mcrs/imicroservice.py
mcrs/launcher.py
mcrs/network.py
mcrs/os_info.py
mcrs/py.typed
mcrs/python_info.py
mcrs/resource_limits.py
mcrs/utils.py
mcrs/cli/__init__.py
mcrs/cli/main.py
mcrs/cli/py.typed
mcrs/cli/utils.py
mcrs/environment/__init__.py
mcrs/environment/exceptions.py
mcrs/environment/imanager.py
mcrs/environment/immutable_dict.py
mcrs/environment/lazy_value.py
mcrs/environment/manager.py
mcrs/environment/py.typed
mcrs/environment/config/__init__.py
mcrs/environment/config/env_conf_value.py
mcrs/environment/config/environment_config.py
mcrs/environment/config/py.typed
mcrs/lifespan/__init__.py
mcrs/lifespan/delayed_interrupt.py
mcrs/lifespan/py.typed
mcrs/lifespan/test_delayed_interrupt.py
mcrs-0.2.3.dist-info/METADATA
mcrs-0.2.3.dist-info/WHEEL
mcrs-0.2.3.dist-info/entry_points.txt
mcrs-0.2.3.dist-info/top_level.txt
mcrs-0.2.3.dist-info/RECORD
