Metadata-Version: 2.1
Name: mcrs
Version: 0.2.3
Summary: Package for microservices
Author: Vladimir Vojtenko
Author-email: vladimirdev635@gmail.com
License: MIT
